{
  "logs": [
    {
      "id": 1,
      "message": "Changed hard drive on workstation 005",
      "attention": false,
      "tech": "Ayra Garcia",
      "date": "2021-07-19T04:10:02.101Z"
    },
    {
      "id": 2,
      "message": "Workstation 007 not posting",
      "attention": true,
      "date": "07-16-2021",
      "tech": "Bonn Ashe"
    },
    {
      "id": 3,
      "message": "Changed memory on workstation 050",
      "attention": false,
      "date": "07-16-2021",
      "tech": "Rhyss Mcree"
    },
    {
      "message": "Hello",
      "attention": true,
      "tech": "Dave Genji",
      "date": "2021-07-19T00:25:10.034Z",
      "id": 4
    }
  ],
  "techs": [
    {
      "id": 1,
      "firstName": "Dave",
      "lastName": "Reaper"
    },
    {
      "id": 2,
      "firstName": "Bonn",
      "lastName": "Ashe"
    },
    {
      "id": 3,
      "firstName": "Rhyss",
      "lastName": "Mcree"
    },
    {
      "firstName": "Ayra",
      "lastName": "Garcia",
      "id": 5
    }
  ]
}